hatch_aws_publisher/__init__.py
hatch_aws_publisher/hooks.py
hatch_aws_publisher/publisher.py
hatch_aws_publisher-0.3.0.dist-info/METADATA
hatch_aws_publisher-0.3.0.dist-info/WHEEL
hatch_aws_publisher-0.3.0.dist-info/entry_points.txt
hatch_aws_publisher-0.3.0.dist-info/licenses/LICENSE.txt
hatch_aws_publisher-0.3.0.dist-info/RECORD
