Metadata-Version: 2.1
Name: hatch-aws-publisher
Version: 0.3.0
Summary: Hatch plugin for deploying to AWS with SAM
Project-URL: Documentation, https://github.com/aka-raccoon/hatch-aws-publishery#readme
Project-URL: Issues, https://github.com/aka-raccoon/hatch-aws-publisher/issues
Project-URL: Source, https://github.com/aka-raccoon/hatch-aws-publisher
Author-email: aka-raccoon <aka-raccoon@pm.me>
License: MIT License
License-File: LICENSE.txt
Keywords: aws,hatch,lambda,plugin,sam
Classifier: Framework :: Hatch
Classifier: Programming Language :: Python
Classifier: Programming Language :: Python :: 3.8
Classifier: Programming Language :: Python :: 3.9
Classifier: Programming Language :: Python :: 3.10
Classifier: Programming Language :: Python :: Implementation :: CPython
Classifier: Programming Language :: Python :: Implementation :: PyPy
Requires-Python: >=3.8
Requires-Dist: hatch
Provides-Extra: dev
Requires-Dist: bandit[toml]; extra == 'dev'
Requires-Dist: black; extra == 'dev'
Requires-Dist: isort; extra == 'dev'
Requires-Dist: mypy; extra == 'dev'
Requires-Dist: pylint; extra == 'dev'
Provides-Extra: test
Requires-Dist: coverage; extra == 'test'
Requires-Dist: pytest; extra == 'test'
Requires-Dist: pytest-cov; extra == 'test'
Requires-Dist: pytest-mock; extra == 'test'
